sqlext/__init__.py
sqlext/sql_ext.py
sqlext/transaction.py
sqlext-0.1.dist-info/DESCRIPTION.rst
sqlext-0.1.dist-info/METADATA
sqlext-0.1.dist-info/RECORD
sqlext-0.1.dist-info/WHEEL
sqlext-0.1.dist-info/metadata.json
sqlext-0.1.dist-info/top_level.txt
